opentargets_urlzsource/__init__.py
opentargets_urlzsource/version.py
opentargets_urlzsource-1.0.0.dist-info/METADATA
opentargets_urlzsource-1.0.0.dist-info/WHEEL
opentargets_urlzsource-1.0.0.dist-info/top_level.txt
opentargets_urlzsource-1.0.0.dist-info/RECORD
