Metadata-Version: 2.1
Name: opentargets-urlzsource
Version: 1.0.0
Summary: File and url handling
Home-page: https://github.com/opentargets/urlzsource
Author: OpenTargets Core Team <support@targetvalidation.org>
Author-email: support@targetvalidation.org
License: Apache License, Version 2.0
Download-URL: https://github.com/opentargets/urlzsource/archive/1.0.0.tar.gz
Keywords: opentargets,python2,python3
Platform: any
Classifier: License :: OSI Approved :: Apache Software License
Classifier: Programming Language :: Python :: 2
Classifier: Programming Language :: Python :: 3
Requires-Dist: requests-file
Requires-Dist: future
Provides-Extra: dev
Requires-Dist: pytest (<4.1.0,>=4.0.0) ; extra == 'dev'
Requires-Dist: pytest-cov ; extra == 'dev'
Requires-Dist: pylint ; extra == 'dev'
Requires-Dist: tox ; extra == 'dev'
Requires-Dist: codecov ; extra == 'dev'
Requires-Dist: pipdeptree ; extra == 'dev'
